main.py
wayscript_cli-0.2.0.dist-info/METADATA
wayscript_cli-0.2.0.dist-info/WHEEL
wayscript_cli-0.2.0.dist-info/entry_points.txt
wayscript_cli-0.2.0.dist-info/top_level.txt
wayscript_cli-0.2.0.dist-info/RECORD
