Metadata-Version: 2.1
Name: wayscript-cli
Version: 0.2.0
Summary: UNKNOWN
Home-page: UNKNOWN
Author: wayscript
License: UNKNOWN
Platform: UNKNOWN
Requires-Python: >=3.6
Requires-Dist: click (==7.1.2)
Requires-Dist: python-engineio (==4.1.0)
Requires-Dist: python-socketio (==5.2.1)
Requires-Dist: requests (==2.25.1)
Requires-Dist: urllib3 (==1.26.4)
Requires-Dist: websocket-client (==0.58.0)
